[
    {
        "parameters": {
            "Ppt_mm_Tot": {
                "lower_bound": 0.0,
                "upper_bound": 1.2353541840212297
            }
        },
        "support": 0.229502196193265,
        "confidence": 0.29673450070989116,
        "lift": 1.2549205200300662,
        "fitness": 0.1321964851043915
    },
    {
        "parameters": {
            "Ppt_mm_Tot": {
                "lower_bound": 0.0,
                "upper_bound": 1.2606328488062293
            }
        },
        "support": 0.229502196193265,
        "confidence": 0.29673450070989116,
        "lift": 1.2549205200300662,
        "fitness": 0.1321964851043915
    },
    {
        "parameters": {
            "Ppt_mm_Tot": {
                "lower_bound": 0.0,
                "upper_bound": 1.2198757314238067
            }
        },
        "support": 0.229502196193265,
        "confidence": 0.29673450070989116,
        "lift": 1.2549205200300662,
        "fitness": 0.1321964851043915
    },
    {
        "parameters": {
            "Ppt_mm_Tot": {
                "lower_bound": 0.0,
                "upper_bound": 1.2568997681525282
            }
        },
        "support": 0.229502196193265,
        "confidence": 0.29673450070989116,
        "lift": 1.2549205200300662,
        "fitness": 0.1321964851043915
    },
    {
        "parameters": {
            "Ppt_mm_Tot": {
                "lower_bound": 0.0,
                "upper_bound": 1.2887427387926513
            }
        },
        "support": 0.229502196193265,
        "confidence": 0.29673450070989116,
        "lift": 1.2549205200300662,
        "fitness": 0.1321964851043915
    },
    {
        "parameters": {
            "Ppt_mm_Tot": {
                "lower_bound": 0.0,
                "upper_bound": 1.2868642099053065
            }
        },
        "support": 0.229502196193265,
        "confidence": 0.29673450070989116,
        "lift": 1.2549205200300662,
        "fitness": 0.1321964851043915
    },
    {
        "parameters": {
            "Ppt_mm_Tot": {
                "lower_bound": 0.0,
                "upper_bound": 1.2353541840212297
            }
        },
        "support": 0.229502196193265,
        "confidence": 0.29673450070989116,
        "lift": 1.2549205200300662,
        "fitness": 0.1321964851043915
    },
    {
        "parameters": {
            "Ppt_mm_Tot": {
                "lower_bound": 0.0,
                "upper_bound": 1.2887427387926513
            }
        },
        "support": 0.229502196193265,
        "confidence": 0.29673450070989116,
        "lift": 1.2549205200300662,
        "fitness": 0.1321964851043915
    },
    {
        "parameters": {
            "Ppt_mm_Tot": {
                "lower_bound": 0.0,
                "upper_bound": 1.2708427959783684
            }
        },
        "support": 0.229502196193265,
        "confidence": 0.29673450070989116,
        "lift": 1.2549205200300662,
        "fitness": 0.1321964851043915
    },
    {
        "parameters": {
            "Ppt_mm_Tot": {
                "lower_bound": 0.0,
                "upper_bound": 1.2708427959783684
            }
        },
        "support": 0.229502196193265,
        "confidence": 0.29673450070989116,
        "lift": 1.2549205200300662,
        "fitness": 0.1321964851043915
    },
    {
        "parameters": {
            "Ppt_mm_Tot": {
                "lower_bound": 0.0,
                "upper_bound": 1.2353541840212297
            }
        },
        "support": 0.229502196193265,
        "confidence": 0.29673450070989116,
        "lift": 1.2549205200300662,
        "fitness": 0.1321964851043915
    },
    {
        "parameters": {
            "Ppt_mm_Tot": {
                "lower_bound": 0.0,
                "upper_bound": 1.2708427959783684
            }
        },
        "support": 0.229502196193265,
        "confidence": 0.29673450070989116,
        "lift": 1.2549205200300662,
        "fitness": 0.1321964851043915
    },
    {
        "parameters": {
            "Ppt_mm_Tot": {
                "lower_bound": 0.0,
                "upper_bound": 1.2715096271385735
            },
            "Relative_Humidity_Min": {
                "lower_bound": 3.4848816630439043,
                "upper_bound": 5.320572048183337
            }
        },
        "support": 0.0010980966325036604,
        "confidence": 0.058823529411764705,
        "lift": 0.2487707157166272,
        "fitness": 5.999435253161502e-07
    },
    {
        "parameters": {
            "Ppt_mm_Tot": {
                "lower_bound": 0.0,
                "upper_bound": 1.266162107682795
            }
        },
        "support": 0.229502196193265,
        "confidence": 0.29673450070989116,
        "lift": 1.2549205200300662,
        "fitness": 0.1321964851043915
    },
    {
        "parameters": {
            "Ppt_mm_Tot": {
                "lower_bound": 0.0,
                "upper_bound": 1.2330055701529212
            }
        },
        "support": 0.229502196193265,
        "confidence": 0.29673450070989116,
        "lift": 1.2549205200300662,
        "fitness": 0.1321964851043915
    },
    {
        "parameters": {
            "Ppt_mm_Tot": {
                "lower_bound": 0.0,
                "upper_bound": 1.2606328488062293
            }
        },
        "support": 0.229502196193265,
        "confidence": 0.29673450070989116,
        "lift": 1.2549205200300662,
        "fitness": 0.1321964851043915
    },
    {
        "parameters": {
            "Ppt_mm_Tot": {
                "lower_bound": 0.22508344598659172,
                "upper_bound": 1.2606328488062293
            }
        },
        "support": 0.0036603221083455345,
        "confidence": 0.1282051282051282,
        "lift": 0.5421925855362387,
        "fitness": 1.452854690936546e-05
    },
    {
        "parameters": {
            "Ppt_mm_Tot": {
                "lower_bound": 0.0,
                "upper_bound": 1.2887427387926513
            }
        },
        "support": 0.229502196193265,
        "confidence": 0.29673450070989116,
        "lift": 1.2549205200300662,
        "fitness": 0.1321964851043915
    },
    {
        "parameters": {
            "Ppt_mm_Tot": {
                "lower_bound": 0.0,
                "upper_bound": 1.2568997681525282
            }
        },
        "support": 0.229502196193265,
        "confidence": 0.29673450070989116,
        "lift": 1.2549205200300662,
        "fitness": 0.1321964851043915
    },
    {
        "parameters": {
            "Ppt_mm_Tot": {
                "lower_bound": 0.0,
                "upper_bound": 1.2353541840212297
            }
        },
        "support": 0.229502196193265,
        "confidence": 0.29673450070989116,
        "lift": 1.2549205200300662,
        "fitness": 0.1321964851043915
    },
    {
        "parameters": {
            "Ppt_mm_Tot": {
                "lower_bound": 0.0,
                "upper_bound": 1.2907263409235639
            }
        },
        "support": 0.229502196193265,
        "confidence": 0.29673450070989116,
        "lift": 1.2549205200300662,
        "fitness": 0.1321964851043915
    },
    {
        "parameters": {
            "Ppt_mm_Tot": {
                "lower_bound": 0.0,
                "upper_bound": 1.2887427387926513
            }
        },
        "support": 0.229502196193265,
        "confidence": 0.29673450070989116,
        "lift": 1.2549205200300662,
        "fitness": 0.1321964851043915
    },
    {
        "parameters": {
            "Ppt_mm_Tot": {
                "lower_bound": 0.0,
                "upper_bound": 1.2887427387926513
            }
        },
        "support": 0.229502196193265,
        "confidence": 0.29673450070989116,
        "lift": 1.2549205200300662,
        "fitness": 0.1321964851043915
    },
    {
        "parameters": {
            "Ppt_mm_Tot": {
                "lower_bound": 0.0,
                "upper_bound": 1.2606328488062293
            }
        },
        "support": 0.229502196193265,
        "confidence": 0.29673450070989116,
        "lift": 1.2549205200300662,
        "fitness": 0.1321964851043915
    },
    {
        "parameters": {
            "Ppt_mm_Tot": {
                "lower_bound": 0.0,
                "upper_bound": 1.2353541840212297
            }
        },
        "support": 0.229502196193265,
        "confidence": 0.29673450070989116,
        "lift": 1.2549205200300662,
        "fitness": 0.1321964851043915
    },
    {
        "parameters": {
            "Ppt_mm_Tot": {
                "lower_bound": 0.0,
                "upper_bound": 1.2887427387926513
            }
        },
        "support": 0.229502196193265,
        "confidence": 0.29673450070989116,
        "lift": 1.2549205200300662,
        "fitness": 0.1321964851043915
    },
    {
        "parameters": {
            "Ppt_mm_Tot": {
                "lower_bound": 0.0,
                "upper_bound": 1.2907263409235639
            }
        },
        "support": 0.229502196193265,
        "confidence": 0.29673450070989116,
        "lift": 1.2549205200300662,
        "fitness": 0.1321964851043915
    },
    {
        "parameters": {
            "Ppt_mm_Tot": {
                "lower_bound": 0.0,
                "upper_bound": 1.2101865142129238
            }
        },
        "support": 0.229502196193265,
        "confidence": 0.29673450070989116,
        "lift": 1.2549205200300662,
        "fitness": 0.1321964851043915
    },
    {
        "parameters": {
            "Ppt_mm_Tot": {
                "lower_bound": 0.0,
                "upper_bound": 1.2606328488062293
            }
        },
        "support": 0.229502196193265,
        "confidence": 0.29673450070989116,
        "lift": 1.2549205200300662,
        "fitness": 0.1321964851043915
    },
    {
        "parameters": {
            "Ppt_mm_Tot": {
                "lower_bound": 0.0,
                "upper_bound": 1.2887427387926513
            }
        },
        "support": 0.229502196193265,
        "confidence": 0.29673450070989116,
        "lift": 1.2549205200300662,
        "fitness": 0.1321964851043915
    },
    {
        "parameters": {
            "Ppt_mm_Tot": {
                "lower_bound": 0.0,
                "upper_bound": 1.2887427387926513
            }
        },
        "support": 0.229502196193265,
        "confidence": 0.29673450070989116,
        "lift": 1.2549205200300662,
        "fitness": 0.1321964851043915
    },
    {
        "parameters": {
            "Ppt_mm_Tot": {
                "lower_bound": 0.0,
                "upper_bound": 1.2353541840212297
            }
        },
        "support": 0.229502196193265,
        "confidence": 0.29673450070989116,
        "lift": 1.2549205200300662,
        "fitness": 0.1321964851043915
    },
    {
        "parameters": {
            "Ppt_mm_Tot": {
                "lower_bound": 0.0,
                "upper_bound": 1.2353541840212297
            }
        },
        "support": 0.229502196193265,
        "confidence": 0.29673450070989116,
        "lift": 1.2549205200300662,
        "fitness": 0.1321964851043915
    },
    {
        "parameters": {
            "Ppt_mm_Tot": {
                "lower_bound": 0.0,
                "upper_bound": 1.2353541840212297
            }
        },
        "support": 0.229502196193265,
        "confidence": 0.29673450070989116,
        "lift": 1.2549205200300662,
        "fitness": 0.1321964851043915
    },
    {
        "parameters": {
            "Ppt_mm_Tot": {
                "lower_bound": 0.0,
                "upper_bound": 1.2568997681525282
            }
        },
        "support": 0.229502196193265,
        "confidence": 0.29673450070989116,
        "lift": 1.2549205200300662,
        "fitness": 0.1321964851043915
    },
    {
        "parameters": {
            "Ppt_mm_Tot": {
                "lower_bound": 0.0,
                "upper_bound": 1.2606328488062293
            }
        },
        "support": 0.229502196193265,
        "confidence": 0.29673450070989116,
        "lift": 1.2549205200300662,
        "fitness": 0.1321964851043915
    },
    {
        "parameters": {
            "Ppt_mm_Tot": {
                "lower_bound": 0.0,
                "upper_bound": 1.2606328488062293
            }
        },
        "support": 0.229502196193265,
        "confidence": 0.29673450070989116,
        "lift": 1.2549205200300662,
        "fitness": 0.1321964851043915
    },
    {
        "parameters": {
            "Ppt_mm_Tot": {
                "lower_bound": 0.0,
                "upper_bound": 1.2353541840212297
            }
        },
        "support": 0.229502196193265,
        "confidence": 0.29673450070989116,
        "lift": 1.2549205200300662,
        "fitness": 0.1321964851043915
    },
    {
        "parameters": {
            "Ppt_mm_Tot": {
                "lower_bound": 0.0,
                "upper_bound": 1.2353541840212297
            }
        },
        "support": 0.229502196193265,
        "confidence": 0.29673450070989116,
        "lift": 1.2549205200300662,
        "fitness": 0.1321964851043915
    },
    {
        "parameters": {
            "Ppt_mm_Tot": {
                "lower_bound": 0.0,
                "upper_bound": 1.2868642099053065
            }
        },
        "support": 0.229502196193265,
        "confidence": 0.29673450070989116,
        "lift": 1.2549205200300662,
        "fitness": 0.1321964851043915
    },
    {
        "parameters": {
            "Ppt_mm_Tot": {
                "lower_bound": 0.0,
                "upper_bound": 1.261176189283072
            }
        },
        "support": 0.229502196193265,
        "confidence": 0.29673450070989116,
        "lift": 1.2549205200300662,
        "fitness": 0.1321964851043915
    },
    {
        "parameters": {
            "Ppt_mm_Tot": {
                "lower_bound": 0.0,
                "upper_bound": 1.2101865142129238
            }
        },
        "support": 0.229502196193265,
        "confidence": 0.29673450070989116,
        "lift": 1.2549205200300662,
        "fitness": 0.1321964851043915
    },
    {
        "parameters": {
            "Ppt_mm_Tot": {
                "lower_bound": 0.0,
                "upper_bound": 1.2198757314238067
            }
        },
        "support": 0.229502196193265,
        "confidence": 0.29673450070989116,
        "lift": 1.2549205200300662,
        "fitness": 0.1321964851043915
    },
    {
        "parameters": {
            "Ppt_mm_Tot": {
                "lower_bound": 0.0,
                "upper_bound": 1.2887427387926513
            }
        },
        "support": 0.229502196193265,
        "confidence": 0.29673450070989116,
        "lift": 1.2549205200300662,
        "fitness": 0.1321964851043915
    },
    {
        "parameters": {
            "Ppt_mm_Tot": {
                "lower_bound": 0.0,
                "upper_bound": 1.2708427959783684
            }
        },
        "support": 0.229502196193265,
        "confidence": 0.29673450070989116,
        "lift": 1.2549205200300662,
        "fitness": 0.1321964851043915
    },
    {
        "parameters": {
            "Ppt_mm_Tot": {
                "lower_bound": 0.0,
                "upper_bound": 1.2887427387926513
            }
        },
        "support": 0.229502196193265,
        "confidence": 0.29673450070989116,
        "lift": 1.2549205200300662,
        "fitness": 0.1321964851043915
    },
    {
        "parameters": {
            "Ppt_mm_Tot": {
                "lower_bound": 0.0,
                "upper_bound": 0.8543955418239177
            }
        },
        "support": 0.2280380673499268,
        "confidence": 0.2986577181208054,
        "lift": 1.2630540029505268,
        "fitness": 0.13136105221966246
    },
    {
        "parameters": {
            "Ppt_mm_Tot": {
                "lower_bound": 0.0,
                "upper_bound": 1.2536011216338179
            }
        },
        "support": 0.229502196193265,
        "confidence": 0.29673450070989116,
        "lift": 1.2549205200300662,
        "fitness": 0.1321964851043915
    },
    {
        "parameters": {
            "Ppt_mm_Tot": {
                "lower_bound": 0.0,
                "upper_bound": 1.2101865142129238
            }
        },
        "support": 0.229502196193265,
        "confidence": 0.29673450070989116,
        "lift": 1.2549205200300662,
        "fitness": 0.1321964851043915
    },
    {
        "parameters": {
            "Ppt_mm_Tot": {
                "lower_bound": 0.0,
                "upper_bound": 1.2708427959783684
            }
        },
        "support": 0.229502196193265,
        "confidence": 0.29673450070989116,
        "lift": 1.2549205200300662,
        "fitness": 0.1321964851043915
    },
    {
        "parameters": {
            "Ppt_mm_Tot": {
                "lower_bound": 0.0,
                "upper_bound": 1.2708427959783684
            }
        },
        "support": 0.229502196193265,
        "confidence": 0.29673450070989116,
        "lift": 1.2549205200300662,
        "fitness": 0.1321964851043915
    },
    {
        "parameters": {
            "Ppt_mm_Tot": {
                "lower_bound": 0.0,
                "upper_bound": 1.2606328488062293
            }
        },
        "support": 0.229502196193265,
        "confidence": 0.29673450070989116,
        "lift": 1.2549205200300662,
        "fitness": 0.1321964851043915
    },
    {
        "parameters": {
            "Ppt_mm_Tot": {
                "lower_bound": 0.0,
                "upper_bound": 1.2101865142129238
            }
        },
        "support": 0.229502196193265,
        "confidence": 0.29673450070989116,
        "lift": 1.2549205200300662,
        "fitness": 0.1321964851043915
    },
    {
        "parameters": {
            "Ppt_mm_Tot": {
                "lower_bound": 0.0,
                "upper_bound": 1.2606328488062293
            }
        },
        "support": 0.229502196193265,
        "confidence": 0.29673450070989116,
        "lift": 1.2549205200300662,
        "fitness": 0.1321964851043915
    },
    {
        "parameters": {
            "Ppt_mm_Tot": {
                "lower_bound": 0.0,
                "upper_bound": 1.2101865142129238
            }
        },
        "support": 0.229502196193265,
        "confidence": 0.29673450070989116,
        "lift": 1.2549205200300662,
        "fitness": 0.1321964851043915
    },
    {
        "parameters": {
            "Ppt_mm_Tot": {
                "lower_bound": 0.0,
                "upper_bound": 1.2887427387926513
            }
        },
        "support": 0.229502196193265,
        "confidence": 0.29673450070989116,
        "lift": 1.2549205200300662,
        "fitness": 0.1321964851043915
    },
    {
        "parameters": {
            "Ppt_mm_Tot": {
                "lower_bound": 0.0,
                "upper_bound": 1.2676452048119558
            }
        },
        "support": 0.229502196193265,
        "confidence": 0.29673450070989116,
        "lift": 1.2549205200300662,
        "fitness": 0.1321964851043915
    },
    {
        "parameters": {
            "Ppt_mm_Tot": {
                "lower_bound": 0.0,
                "upper_bound": 1.2101865142129238
            }
        },
        "support": 0.229502196193265,
        "confidence": 0.29673450070989116,
        "lift": 1.2549205200300662,
        "fitness": 0.1321964851043915
    },
    {
        "parameters": {
            "Ppt_mm_Tot": {
                "lower_bound": 0.0,
                "upper_bound": 1.2606328488062293
            }
        },
        "support": 0.229502196193265,
        "confidence": 0.29673450070989116,
        "lift": 1.2549205200300662,
        "fitness": 0.1321964851043915
    },
    {
        "parameters": {
            "Ppt_mm_Tot": {
                "lower_bound": 0.0,
                "upper_bound": 1.2568997681525282
            }
        },
        "support": 0.229502196193265,
        "confidence": 0.29673450070989116,
        "lift": 1.2549205200300662,
        "fitness": 0.1321964851043915
    },
    {
        "parameters": {
            "Ppt_mm_Tot": {
                "lower_bound": 0.0,
                "upper_bound": 1.2887427387926513
            }
        },
        "support": 0.229502196193265,
        "confidence": 0.29673450070989116,
        "lift": 1.2549205200300662,
        "fitness": 0.1321964851043915
    },
    {
        "parameters": {
            "Ppt_mm_Tot": {
                "lower_bound": 0.0,
                "upper_bound": 1.2606328488062293
            }
        },
        "support": 0.229502196193265,
        "confidence": 0.29673450070989116,
        "lift": 1.2549205200300662,
        "fitness": 0.1321964851043915
    },
    {
        "parameters": {
            "Ppt_mm_Tot": {
                "lower_bound": 0.0,
                "upper_bound": 1.2868642099053065
            }
        },
        "support": 0.229502196193265,
        "confidence": 0.29673450070989116,
        "lift": 1.2549205200300662,
        "fitness": 0.1321964851043915
    },
    {
        "parameters": {
            "Ppt_mm_Tot": {
                "lower_bound": 0.0,
                "upper_bound": 1.2606328488062293
            }
        },
        "support": 0.229502196193265,
        "confidence": 0.29673450070989116,
        "lift": 1.2549205200300662,
        "fitness": 0.1321964851043915
    },
    {
        "parameters": {
            "Ppt_mm_Tot": {
                "lower_bound": 0.0,
                "upper_bound": 1.2887427387926513
            }
        },
        "support": 0.229502196193265,
        "confidence": 0.29673450070989116,
        "lift": 1.2549205200300662,
        "fitness": 0.1321964851043915
    },
    {
        "parameters": {
            "Ppt_mm_Tot": {
                "lower_bound": 0.0,
                "upper_bound": 1.2330055701529212
            }
        },
        "support": 0.229502196193265,
        "confidence": 0.29673450070989116,
        "lift": 1.2549205200300662,
        "fitness": 0.1321964851043915
    },
    {
        "parameters": {
            "Ppt_mm_Tot": {
                "lower_bound": 0.0,
                "upper_bound": 1.2938733977747325
            }
        },
        "support": 0.229502196193265,
        "confidence": 0.29673450070989116,
        "lift": 1.2549205200300662,
        "fitness": 0.1321964851043915
    },
    {
        "parameters": {
            "Ppt_mm_Tot": {
                "lower_bound": 0.0,
                "upper_bound": 1.2536011216338179
            },
            "Relative_Humidity_Max": {
                "lower_bound": 83.64232627796461,
                "upper_bound": 87.7557581431288
            }
        },
        "support": 0.016471449487554905,
        "confidence": 0.3629032258064516,
        "lift": 1.5347548187356437,
        "fitness": 0.00083278451044389
    },
    {
        "parameters": {
            "Ppt_mm_Tot": {
                "lower_bound": 0.0,
                "upper_bound": 1.2198757314238067
            }
        },
        "support": 0.229502196193265,
        "confidence": 0.29673450070989116,
        "lift": 1.2549205200300662,
        "fitness": 0.1321964851043915
    },
    {
        "parameters": {
            "Ppt_mm_Tot": {
                "lower_bound": 0.0,
                "upper_bound": 1.2353541840212297
            }
        },
        "support": 0.229502196193265,
        "confidence": 0.29673450070989116,
        "lift": 1.2549205200300662,
        "fitness": 0.1321964851043915
    },
    {
        "parameters": {
            "Ppt_mm_Tot": {
                "lower_bound": 0.0,
                "upper_bound": 0.9332408450206726
            }
        },
        "support": 0.22840409956076135,
        "confidence": 0.29770992366412213,
        "lift": 1.2590456833597239,
        "fitness": 0.13136487998749058
    },
    {
        "parameters": {
            "Ppt_mm_Tot": {
                "lower_bound": 0.0,
                "upper_bound": 1.2708427959783684
            }
        },
        "support": 0.229502196193265,
        "confidence": 0.29673450070989116,
        "lift": 1.2549205200300662,
        "fitness": 0.1321964851043915
    },
    {
        "parameters": {
            "Ppt_mm_Tot": {
                "lower_bound": 0.0,
                "upper_bound": 1.2353541840212297
            }
        },
        "support": 0.229502196193265,
        "confidence": 0.29673450070989116,
        "lift": 1.2549205200300662,
        "fitness": 0.1321964851043915
    },
    {
        "parameters": {
            "Ppt_mm_Tot": {
                "lower_bound": 0.0,
                "upper_bound": 1.2101865142129238
            }
        },
        "support": 0.229502196193265,
        "confidence": 0.29673450070989116,
        "lift": 1.2549205200300662,
        "fitness": 0.1321964851043915
    },
    {
        "parameters": {
            "Ppt_mm_Tot": {
                "lower_bound": 0.0,
                "upper_bound": 1.2101865142129238
            }
        },
        "support": 0.229502196193265,
        "confidence": 0.29673450070989116,
        "lift": 1.2549205200300662,
        "fitness": 0.1321964851043915
    },
    {
        "parameters": {
            "Ppt_mm_Tot": {
                "lower_bound": 0.0,
                "upper_bound": 1.2606328488062293
            }
        },
        "support": 0.229502196193265,
        "confidence": 0.29673450070989116,
        "lift": 1.2549205200300662,
        "fitness": 0.1321964851043915
    },
    {
        "parameters": {
            "Ppt_mm_Tot": {
                "lower_bound": 0.0,
                "upper_bound": 1.2887427387926513
            },
            "Relative_Humidity_Avg": {
                "lower_bound": 11.13844966927508,
                "upper_bound": 12.207371965374117
            }
        },
        "support": 0.0,
        "confidence": 0.0,
        "lift": 0.0,
        "fitness": 0.0
    },
    {
        "parameters": {
            "Ppt_mm_Tot": {
                "lower_bound": 0.0,
                "upper_bound": 1.2938733977747325
            }
        },
        "support": 0.229502196193265,
        "confidence": 0.29673450070989116,
        "lift": 1.2549205200300662,
        "fitness": 0.1321964851043915
    },
    {
        "parameters": {
            "Ppt_mm_Tot": {
                "lower_bound": 0.0,
                "upper_bound": 1.2868642099053065
            }
        },
        "support": 0.229502196193265,
        "confidence": 0.29673450070989116,
        "lift": 1.2549205200300662,
        "fitness": 0.1321964851043915
    },
    {
        "parameters": {
            "Ppt_mm_Tot": {
                "lower_bound": 0.0,
                "upper_bound": 1.2101865142129238
            }
        },
        "support": 0.229502196193265,
        "confidence": 0.29673450070989116,
        "lift": 1.2549205200300662,
        "fitness": 0.1321964851043915
    },
    {
        "parameters": {
            "Ppt_mm_Tot": {
                "lower_bound": 0.0,
                "upper_bound": 1.2353541840212297
            }
        },
        "support": 0.229502196193265,
        "confidence": 0.29673450070989116,
        "lift": 1.2549205200300662,
        "fitness": 0.1321964851043915
    },
    {
        "parameters": {
            "Ppt_mm_Tot": {
                "lower_bound": 0.0,
                "upper_bound": 1.2353541840212297
            }
        },
        "support": 0.229502196193265,
        "confidence": 0.29673450070989116,
        "lift": 1.2549205200300662,
        "fitness": 0.1321964851043915
    },
    {
        "parameters": {
            "Ppt_mm_Tot": {
                "lower_bound": 0.0,
                "upper_bound": 1.2101865142129238
            }
        },
        "support": 0.229502196193265,
        "confidence": 0.29673450070989116,
        "lift": 1.2549205200300662,
        "fitness": 0.1321964851043915
    },
    {
        "parameters": {
            "Ppt_mm_Tot": {
                "lower_bound": 0.0,
                "upper_bound": 0.8740886458891686
            }
        },
        "support": 0.2280380673499268,
        "confidence": 0.2986577181208054,
        "lift": 1.2630540029505268,
        "fitness": 0.13136105221966246
    },
    {
        "parameters": {
            "Ppt_mm_Tot": {
                "lower_bound": 0.0,
                "upper_bound": 1.2353541840212297
            }
        },
        "support": 0.229502196193265,
        "confidence": 0.29673450070989116,
        "lift": 1.2549205200300662,
        "fitness": 0.1321964851043915
    },
    {
        "parameters": {
            "Ppt_mm_Tot": {
                "lower_bound": 0.0,
                "upper_bound": 1.2606328488062293
            }
        },
        "support": 0.229502196193265,
        "confidence": 0.29673450070989116,
        "lift": 1.2549205200300662,
        "fitness": 0.1321964851043915
    },
    {
        "parameters": {
            "Ppt_mm_Tot": {
                "lower_bound": 0.0,
                "upper_bound": 1.2868642099053065
            }
        },
        "support": 0.229502196193265,
        "confidence": 0.29673450070989116,
        "lift": 1.2549205200300662,
        "fitness": 0.1321964851043915
    },
    {
        "parameters": {
            "Ppt_mm_Tot": {
                "lower_bound": 0.0,
                "upper_bound": 1.2887427387926513
            }
        },
        "support": 0.229502196193265,
        "confidence": 0.29673450070989116,
        "lift": 1.2549205200300662,
        "fitness": 0.1321964851043915
    },
    {
        "parameters": {
            "Ppt_mm_Tot": {
                "lower_bound": 0.0,
                "upper_bound": 1.2708427959783684
            }
        },
        "support": 0.229502196193265,
        "confidence": 0.29673450070989116,
        "lift": 1.2549205200300662,
        "fitness": 0.1321964851043915
    },
    {
        "parameters": {
            "Ppt_mm_Tot": {
                "lower_bound": 0.0,
                "upper_bound": 1.2606328488062293
            }
        },
        "support": 0.229502196193265,
        "confidence": 0.29673450070989116,
        "lift": 1.2549205200300662,
        "fitness": 0.1321964851043915
    },
    {
        "parameters": {
            "Ppt_mm_Tot": {
                "lower_bound": 0.0,
                "upper_bound": 1.266162107682795
            }
        },
        "support": 0.229502196193265,
        "confidence": 0.29673450070989116,
        "lift": 1.2549205200300662,
        "fitness": 0.1321964851043915
    },
    {
        "parameters": {
            "Ppt_mm_Tot": {
                "lower_bound": 0.0,
                "upper_bound": 1.2708427959783684
            }
        },
        "support": 0.229502196193265,
        "confidence": 0.29673450070989116,
        "lift": 1.2549205200300662,
        "fitness": 0.1321964851043915
    },
    {
        "parameters": {
            "Ppt_mm_Tot": {
                "lower_bound": 0.0,
                "upper_bound": 1.2101865142129238
            }
        },
        "support": 0.229502196193265,
        "confidence": 0.29673450070989116,
        "lift": 1.2549205200300662,
        "fitness": 0.1321964851043915
    },
    {
        "parameters": {
            "Ppt_mm_Tot": {
                "lower_bound": 0.0,
                "upper_bound": 1.2887427387926513
            }
        },
        "support": 0.229502196193265,
        "confidence": 0.29673450070989116,
        "lift": 1.2549205200300662,
        "fitness": 0.1321964851043915
    },
    {
        "parameters": {
            "Ppt_mm_Tot": {
                "lower_bound": 0.0,
                "upper_bound": 1.2887427387926513
            }
        },
        "support": 0.229502196193265,
        "confidence": 0.29673450070989116,
        "lift": 1.2549205200300662,
        "fitness": 0.1321964851043915
    },
    {
        "parameters": {
            "Ppt_mm_Tot": {
                "lower_bound": 0.0,
                "upper_bound": 1.2353541840212297
            }
        },
        "support": 0.229502196193265,
        "confidence": 0.29673450070989116,
        "lift": 1.2549205200300662,
        "fitness": 0.1321964851043915
    },
    {
        "parameters": {
            "Ppt_mm_Tot": {
                "lower_bound": 0.0,
                "upper_bound": 1.2887427387926513
            }
        },
        "support": 0.229502196193265,
        "confidence": 0.29673450070989116,
        "lift": 1.2549205200300662,
        "fitness": 0.1321964851043915
    },
    {
        "parameters": {
            "Ppt_mm_Tot": {
                "lower_bound": 0.0,
                "upper_bound": 1.2705196935106937
            }
        },
        "support": 0.229502196193265,
        "confidence": 0.29673450070989116,
        "lift": 1.2549205200300662,
        "fitness": 0.1321964851043915
    },
    {
        "parameters": {
            "Ppt_mm_Tot": {
                "lower_bound": 0.0,
                "upper_bound": 1.2330055701529212
            }
        },
        "support": 0.229502196193265,
        "confidence": 0.29673450070989116,
        "lift": 1.2549205200300662,
        "fitness": 0.1321964851043915
    },
    {
        "parameters": {
            "Ppt_mm_Tot": {
                "lower_bound": 0.0,
                "upper_bound": 1.2101865142129238
            }
        },
        "support": 0.229502196193265,
        "confidence": 0.29673450070989116,
        "lift": 1.2549205200300662,
        "fitness": 0.1321964851043915
    },
    {
        "parameters": {
            "Ppt_mm_Tot": {
                "lower_bound": 0.0,
                "upper_bound": 1.2198757314238067
            }
        },
        "support": 0.229502196193265,
        "confidence": 0.29673450070989116,
        "lift": 1.2549205200300662,
        "fitness": 0.1321964851043915
    },
    {
        "parameters": {
            "Ppt_mm_Tot": {
                "lower_bound": 0.0,
                "upper_bound": 1.2101865142129238
            }
        },
        "support": 0.229502196193265,
        "confidence": 0.29673450070989116,
        "lift": 1.2549205200300662,
        "fitness": 0.1321964851043915
    },
    {
        "parameters": {
            "Ppt_mm_Tot": {
                "lower_bound": 0.0,
                "upper_bound": 1.2938733977747325
            }
        },
        "support": 0.229502196193265,
        "confidence": 0.29673450070989116,
        "lift": 1.2549205200300662,
        "fitness": 0.1321964851043915
    },
    {
        "parameters": {
            "Ppt_mm_Tot": {
                "lower_bound": 0.0,
                "upper_bound": 1.2353541840212297
            }
        },
        "support": 0.229502196193265,
        "confidence": 0.29673450070989116,
        "lift": 1.2549205200300662,
        "fitness": 0.1321964851043915
    },
    {
        "parameters": {
            "Ppt_mm_Tot": {
                "lower_bound": 0.0,
                "upper_bound": 1.2568997681525282
            }
        },
        "support": 0.229502196193265,
        "confidence": 0.29673450070989116,
        "lift": 1.2549205200300662,
        "fitness": 0.1321964851043915
    },
    {
        "parameters": {
            "Ppt_mm_Tot": {
                "lower_bound": 0.0,
                "upper_bound": 1.2101865142129238
            }
        },
        "support": 0.229502196193265,
        "confidence": 0.29673450070989116,
        "lift": 1.2549205200300662,
        "fitness": 0.1321964851043915
    },
    {
        "parameters": {
            "Ppt_mm_Tot": {
                "lower_bound": 0.0,
                "upper_bound": 1.2536011216338179
            }
        },
        "support": 0.229502196193265,
        "confidence": 0.29673450070989116,
        "lift": 1.2549205200300662,
        "fitness": 0.1321964851043915
    },
    {
        "parameters": {
            "Ppt_mm_Tot": {
                "lower_bound": 0.0,
                "upper_bound": 1.2606328488062293
            }
        },
        "support": 0.229502196193265,
        "confidence": 0.29673450070989116,
        "lift": 1.2549205200300662,
        "fitness": 0.1321964851043915
    },
    {
        "parameters": {
            "Ppt_mm_Tot": {
                "lower_bound": 0.0,
                "upper_bound": 1.2868642099053065
            }
        },
        "support": 0.229502196193265,
        "confidence": 0.29673450070989116,
        "lift": 1.2549205200300662,
        "fitness": 0.1321964851043915
    },
    {
        "parameters": {
            "Ppt_mm_Tot": {
                "lower_bound": 0.0,
                "upper_bound": 1.2353541840212297
            }
        },
        "support": 0.229502196193265,
        "confidence": 0.29673450070989116,
        "lift": 1.2549205200300662,
        "fitness": 0.1321964851043915
    },
    {
        "parameters": {
            "Ppt_mm_Tot": {
                "lower_bound": 0.0,
                "upper_bound": 1.2606328488062293
            }
        },
        "support": 0.229502196193265,
        "confidence": 0.29673450070989116,
        "lift": 1.2549205200300662,
        "fitness": 0.1321964851043915
    },
    {
        "parameters": {
            "Ppt_mm_Tot": {
                "lower_bound": 0.0,
                "upper_bound": 1.2606328488062293
            }
        },
        "support": 0.229502196193265,
        "confidence": 0.29673450070989116,
        "lift": 1.2549205200300662,
        "fitness": 0.1321964851043915
    },
    {
        "parameters": {
            "Ppt_mm_Tot": {
                "lower_bound": 0.0,
                "upper_bound": 1.2868642099053065
            }
        },
        "support": 0.229502196193265,
        "confidence": 0.29673450070989116,
        "lift": 1.2549205200300662,
        "fitness": 0.1321964851043915
    },
    {
        "parameters": {
            "Ppt_mm_Tot": {
                "lower_bound": 0.0,
                "upper_bound": 1.2868642099053065
            }
        },
        "support": 0.229502196193265,
        "confidence": 0.29673450070989116,
        "lift": 1.2549205200300662,
        "fitness": 0.1321964851043915
    },
    {
        "parameters": {
            "Ppt_mm_Tot": {
                "lower_bound": 0.0,
                "upper_bound": 1.2101865142129238
            }
        },
        "support": 0.229502196193265,
        "confidence": 0.29673450070989116,
        "lift": 1.2549205200300662,
        "fitness": 0.1321964851043915
    },
    {
        "parameters": {
            "Ppt_mm_Tot": {
                "lower_bound": 0.0,
                "upper_bound": 1.2353541840212297
            }
        },
        "support": 0.229502196193265,
        "confidence": 0.29673450070989116,
        "lift": 1.2549205200300662,
        "fitness": 0.1321964851043915
    },
    {
        "parameters": {
            "Ppt_mm_Tot": {
                "lower_bound": 0.0,
                "upper_bound": 1.2101865142129238
            }
        },
        "support": 0.229502196193265,
        "confidence": 0.29673450070989116,
        "lift": 1.2549205200300662,
        "fitness": 0.1321964851043915
    },
    {
        "parameters": {
            "Ppt_mm_Tot": {
                "lower_bound": 0.0,
                "upper_bound": 1.2887427387926513
            }
        },
        "support": 0.229502196193265,
        "confidence": 0.29673450070989116,
        "lift": 1.2549205200300662,
        "fitness": 0.1321964851043915
    },
    {
        "parameters": {
            "Ppt_mm_Tot": {
                "lower_bound": 0.0,
                "upper_bound": 1.2353541840212297
            }
        },
        "support": 0.229502196193265,
        "confidence": 0.29673450070989116,
        "lift": 1.2549205200300662,
        "fitness": 0.1321964851043915
    },
    {
        "parameters": {
            "Ppt_mm_Tot": {
                "lower_bound": 0.0,
                "upper_bound": 1.263905968604392
            }
        },
        "support": 0.229502196193265,
        "confidence": 0.29673450070989116,
        "lift": 1.2549205200300662,
        "fitness": 0.1321964851043915
    },
    {
        "parameters": {
            "Ppt_mm_Tot": {
                "lower_bound": 0.0,
                "upper_bound": 1.0784082590819997
            }
        },
        "support": 0.2287701317715959,
        "confidence": 0.2976190476190476,
        "lift": 1.2586613592805544,
        "fitness": 0.13174603084664552
    },
    {
        "parameters": {
            "Ppt_mm_Tot": {
                "lower_bound": 0.0,
                "upper_bound": 1.2887427387926513
            }
        },
        "support": 0.229502196193265,
        "confidence": 0.29673450070989116,
        "lift": 1.2549205200300662,
        "fitness": 0.1321964851043915
    },
    {
        "parameters": {
            "Ppt_mm_Tot": {
                "lower_bound": 0.0,
                "upper_bound": 1.2568997681525282
            }
        },
        "support": 0.229502196193265,
        "confidence": 0.29673450070989116,
        "lift": 1.2549205200300662,
        "fitness": 0.1321964851043915
    },
    {
        "parameters": {
            "Ppt_mm_Tot": {
                "lower_bound": 0.0,
                "upper_bound": 1.2708427959783684
            }
        },
        "support": 0.229502196193265,
        "confidence": 0.29673450070989116,
        "lift": 1.2549205200300662,
        "fitness": 0.1321964851043915
    },
    {
        "parameters": {
            "Ppt_mm_Tot": {
                "lower_bound": 0.0,
                "upper_bound": 1.2938733977747325
            }
        },
        "support": 0.229502196193265,
        "confidence": 0.29673450070989116,
        "lift": 1.2549205200300662,
        "fitness": 0.1321964851043915
    },
    {
        "parameters": {
            "Ppt_mm_Tot": {
                "lower_bound": 0.0,
                "upper_bound": 1.2606328488062293
            }
        },
        "support": 0.229502196193265,
        "confidence": 0.29673450070989116,
        "lift": 1.2549205200300662,
        "fitness": 0.1321964851043915
    },
    {
        "parameters": {
            "Ppt_mm_Tot": {
                "lower_bound": 0.0439451391868216,
                "upper_bound": 1.2353541840212297
            }
        },
        "support": 0.011346998535871157,
        "confidence": 0.17032967032967034,
        "lift": 0.7203415779267173,
        "fitness": 0.0001854942604186742
    },
    {
        "parameters": {
            "Ppt_mm_Tot": {
                "lower_bound": 0.0,
                "upper_bound": 1.2636222596527926
            }
        },
        "support": 0.229502196193265,
        "confidence": 0.29673450070989116,
        "lift": 1.2549205200300662,
        "fitness": 0.1321964851043915
    },
    {
        "parameters": {
            "Ppt_mm_Tot": {
                "lower_bound": 0.0,
                "upper_bound": 1.2353541840212297
            }
        },
        "support": 0.229502196193265,
        "confidence": 0.29673450070989116,
        "lift": 1.2549205200300662,
        "fitness": 0.1321964851043915
    },
    {
        "parameters": {
            "Ppt_mm_Tot": {
                "lower_bound": 0.0,
                "upper_bound": 1.2868642099053065
            }
        },
        "support": 0.229502196193265,
        "confidence": 0.29673450070989116,
        "lift": 1.2549205200300662,
        "fitness": 0.1321964851043915
    },
    {
        "parameters": {
            "Ppt_mm_Tot": {
                "lower_bound": 0.0,
                "upper_bound": 1.2606328488062293
            }
        },
        "support": 0.229502196193265,
        "confidence": 0.29673450070989116,
        "lift": 1.2549205200300662,
        "fitness": 0.1321964851043915
    },
    {
        "parameters": {
            "Ppt_mm_Tot": {
                "lower_bound": 0.0,
                "upper_bound": 1.2198757314238067
            }
        },
        "support": 0.229502196193265,
        "confidence": 0.29673450070989116,
        "lift": 1.2549205200300662,
        "fitness": 0.1321964851043915
    },
    {
        "parameters": {
            "Ppt_mm_Tot": {
                "lower_bound": 0.0,
                "upper_bound": 1.2101865142129238
            },
            "Air_TempC_Min": {
                "lower_bound": 9.282295693211703,
                "upper_bound": 10.034233639248546
            }
        },
        "support": 0.0,
        "confidence": 0.0,
        "lift": 0.0,
        "fitness": 0.0
    },
    {
        "parameters": {
            "Ppt_mm_Tot": {
                "lower_bound": 0.0,
                "upper_bound": 1.2330055701529212
            }
        },
        "support": 0.229502196193265,
        "confidence": 0.29673450070989116,
        "lift": 1.2549205200300662,
        "fitness": 0.1321964851043915
    },
    {
        "parameters": {
            "Ppt_mm_Tot": {
                "lower_bound": 0.0,
                "upper_bound": 1.2330055701529212
            },
            "Air_TempC_Min": {
                "lower_bound": -4.468458054658896,
                "upper_bound": -3.086388334999869
            }
        },
        "support": 0.029282576866764276,
        "confidence": 1.0,
        "lift": 4.2291021671826625,
        "fitness": 0.007252650617155239
    },
    {
        "parameters": {
            "Ppt_mm_Tot": {
                "lower_bound": 0.3897698931168487,
                "upper_bound": 1.2353541840212297
            }
        },
        "support": 0.003294289897510981,
        "confidence": 0.13636363636363635,
        "lift": 0.576695750070363,
        "fitness": 1.2517003550914226e-05
    },
    {
        "parameters": {
            "Ppt_mm_Tot": {
                "lower_bound": 0.0,
                "upper_bound": 1.2938733977747325
            }
        },
        "support": 0.229502196193265,
        "confidence": 0.29673450070989116,
        "lift": 1.2549205200300662,
        "fitness": 0.1321964851043915
    },
    {
        "parameters": {
            "Ppt_mm_Tot": {
                "lower_bound": 0.0,
                "upper_bound": 1.2708427959783684
            }
        },
        "support": 0.229502196193265,
        "confidence": 0.29673450070989116,
        "lift": 1.2549205200300662,
        "fitness": 0.1321964851043915
    },
    {
        "parameters": {
            "Ppt_mm_Tot": {
                "lower_bound": 0.0,
                "upper_bound": 1.2907263409235639
            }
        },
        "support": 0.229502196193265,
        "confidence": 0.29673450070989116,
        "lift": 1.2549205200300662,
        "fitness": 0.1321964851043915
    },
    {
        "parameters": {
            "Ppt_mm_Tot": {
                "lower_bound": 0.0,
                "upper_bound": 1.2887427387926513
            }
        },
        "support": 0.229502196193265,
        "confidence": 0.29673450070989116,
        "lift": 1.2549205200300662,
        "fitness": 0.1321964851043915
    },
    {
        "parameters": {
            "Ppt_mm_Tot": {
                "lower_bound": 0.0,
                "upper_bound": 1.2568997681525282
            }
        },
        "support": 0.229502196193265,
        "confidence": 0.29673450070989116,
        "lift": 1.2549205200300662,
        "fitness": 0.1321964851043915
    },
    {
        "parameters": {
            "Ppt_mm_Tot": {
                "lower_bound": 0.0,
                "upper_bound": 1.2887427387926513
            }
        },
        "support": 0.229502196193265,
        "confidence": 0.29673450070989116,
        "lift": 1.2549205200300662,
        "fitness": 0.1321964851043915
    },
    {
        "parameters": {
            "Ppt_mm_Tot": {
                "lower_bound": 0.0,
                "upper_bound": 1.2606328488062293
            },
            "Relative_Humidity_Avg": {
                "lower_bound": 53.960039815115366,
                "upper_bound": 55.5845163227488
            }
        },
        "support": 0.005856515373352855,
        "confidence": 0.36363636363636365,
        "lift": 1.5378553335209684,
        "fitness": 0.00010549309988589438
    },
    {
        "parameters": {
            "Ppt_mm_Tot": {
                "lower_bound": 0.0,
                "upper_bound": 1.2353541840212297
            }
        },
        "support": 0.229502196193265,
        "confidence": 0.29673450070989116,
        "lift": 1.2549205200300662,
        "fitness": 0.1321964851043915
    },
    {
        "parameters": {
            "Ppt_mm_Tot": {
                "lower_bound": 0.0,
                "upper_bound": 1.1223595608226886
            }
        },
        "support": 0.2287701317715959,
        "confidence": 0.2970532319391635,
        "lift": 1.2562684669625306,
        "fitness": 0.13149556310739333
    },
    {
        "parameters": {
            "Ppt_mm_Tot": {
                "lower_bound": 0.0,
                "upper_bound": 1.2606328488062293
            }
        },
        "support": 0.229502196193265,
        "confidence": 0.29673450070989116,
        "lift": 1.2549205200300662,
        "fitness": 0.1321964851043915
    },
    {
        "parameters": {
            "Ppt_mm_Tot": {
                "lower_bound": 0.0,
                "upper_bound": 1.2353541840212297
            }
        },
        "support": 0.229502196193265,
        "confidence": 0.29673450070989116,
        "lift": 1.2549205200300662,
        "fitness": 0.1321964851043915
    },
    {
        "parameters": {
            "Ppt_mm_Tot": {
                "lower_bound": 0.0,
                "upper_bound": 1.2101865142129238
            }
        },
        "support": 0.229502196193265,
        "confidence": 0.29673450070989116,
        "lift": 1.2549205200300662,
        "fitness": 0.1321964851043915
    },
    {
        "parameters": {
            "Ppt_mm_Tot": {
                "lower_bound": 0.0,
                "upper_bound": 1.2887427387926513
            }
        },
        "support": 0.229502196193265,
        "confidence": 0.29673450070989116,
        "lift": 1.2549205200300662,
        "fitness": 0.1321964851043915
    },
    {
        "parameters": {
            "Ppt_mm_Tot": {
                "lower_bound": 0.0,
                "upper_bound": 1.2887427387926513
            }
        },
        "support": 0.229502196193265,
        "confidence": 0.29673450070989116,
        "lift": 1.2549205200300662,
        "fitness": 0.1321964851043915
    },
    {
        "parameters": {
            "Ppt_mm_Tot": {
                "lower_bound": 0.0,
                "upper_bound": 1.2606328488062293
            },
            "Relative_Humidity_Min": {
                "lower_bound": 50.40697617385842,
                "upper_bound": 52.63149183488791
            }
        },
        "support": 0.0010980966325036604,
        "confidence": 0.42857142857142855,
        "lift": 1.8124723573639983,
        "fitness": 4.371017113017666e-06
    },
    {
        "parameters": {
            "Ppt_mm_Tot": {
                "lower_bound": 0.0,
                "upper_bound": 1.2606328488062293
            }
        },
        "support": 0.229502196193265,
        "confidence": 0.29673450070989116,
        "lift": 1.2549205200300662,
        "fitness": 0.1321964851043915
    },
    {
        "parameters": {
            "Ppt_mm_Tot": {
                "lower_bound": 0.0,
                "upper_bound": 0.97691955357684
            }
        },
        "support": 0.22840409956076135,
        "confidence": 0.29770992366412213,
        "lift": 1.2590456833597239,
        "fitness": 0.13136487998749058
    },
    {
        "parameters": {
            "Ppt_mm_Tot": {
                "lower_bound": 0.0,
                "upper_bound": 1.2606328488062293
            }
        },
        "support": 0.229502196193265,
        "confidence": 0.29673450070989116,
        "lift": 1.2549205200300662,
        "fitness": 0.1321964851043915
    },
    {
        "parameters": {
            "Ppt_mm_Tot": {
                "lower_bound": 0.0,
                "upper_bound": 1.2101865142129238
            }
        },
        "support": 0.229502196193265,
        "confidence": 0.29673450070989116,
        "lift": 1.2549205200300662,
        "fitness": 0.1321964851043915
    },
    {
        "parameters": {
            "Ppt_mm_Tot": {
                "lower_bound": 0.0,
                "upper_bound": 1.2887427387926513
            }
        },
        "support": 0.229502196193265,
        "confidence": 0.29673450070989116,
        "lift": 1.2549205200300662,
        "fitness": 0.1321964851043915
    },
    {
        "parameters": {
            "Ppt_mm_Tot": {
                "lower_bound": 0.3374359961753344,
                "upper_bound": 1.2868642099053065
            }
        },
        "support": 0.003294289897510981,
        "confidence": 0.13636363636363635,
        "lift": 0.576695750070363,
        "fitness": 1.2517003550914226e-05
    },
    {
        "parameters": {
            "Ppt_mm_Tot": {
                "lower_bound": 0.0,
                "upper_bound": 1.2568997681525282
            }
        },
        "support": 0.229502196193265,
        "confidence": 0.29673450070989116,
        "lift": 1.2549205200300662,
        "fitness": 0.1321964851043915
    },
    {
        "parameters": {
            "Ppt_mm_Tot": {
                "lower_bound": 0.0,
                "upper_bound": 1.2907263409235639
            }
        },
        "support": 0.229502196193265,
        "confidence": 0.29673450070989116,
        "lift": 1.2549205200300662,
        "fitness": 0.1321964851043915
    },
    {
        "parameters": {
            "Ppt_mm_Tot": {
                "lower_bound": 0.0,
                "upper_bound": 1.2708427959783684
            }
        },
        "support": 0.229502196193265,
        "confidence": 0.29673450070989116,
        "lift": 1.2549205200300662,
        "fitness": 0.1321964851043915
    },
    {
        "parameters": {
            "Ppt_mm_Tot": {
                "lower_bound": 0.0,
                "upper_bound": 1.2536011216338179
            }
        },
        "support": 0.229502196193265,
        "confidence": 0.29673450070989116,
        "lift": 1.2549205200300662,
        "fitness": 0.1321964851043915
    },
    {
        "parameters": {
            "Ppt_mm_Tot": {
                "lower_bound": 0.0,
                "upper_bound": 1.2606328488062293
            }
        },
        "support": 0.229502196193265,
        "confidence": 0.29673450070989116,
        "lift": 1.2549205200300662,
        "fitness": 0.1321964851043915
    },
    {
        "parameters": {
            "Ppt_mm_Tot": {
                "lower_bound": 0.0,
                "upper_bound": 1.2101865142129238
            },
            "Relative_Humidity_Max": {
                "lower_bound": 69.37154222632954,
                "upper_bound": 73.14291781918249
            }
        },
        "support": 0.01281112737920937,
        "confidence": 0.35353535353535354,
        "lift": 1.4951371298120524,
        "fitness": 0.0004907787171883378
    },
    {
        "parameters": {
            "Ppt_mm_Tot": {
                "lower_bound": 0.0,
                "upper_bound": 1.2708427959783684
            }
        },
        "support": 0.229502196193265,
        "confidence": 0.29673450070989116,
        "lift": 1.2549205200300662,
        "fitness": 0.1321964851043915
    },
    {
        "parameters": {
            "Ppt_mm_Tot": {
                "lower_bound": 0.0,
                "upper_bound": 1.2715096271385735
            }
        },
        "support": 0.229502196193265,
        "confidence": 0.29673450070989116,
        "lift": 1.2549205200300662,
        "fitness": 0.1321964851043915
    },
    {
        "parameters": {
            "Ppt_mm_Tot": {
                "lower_bound": 0.0,
                "upper_bound": 1.2101865142129238
            },
            "Air_TempC_Max": {
                "lower_bound": 13.91281021674606,
                "upper_bound": 14.746783992338889
            }
        },
        "support": 0.014275256222547585,
        "confidence": 0.9069767441860465,
        "lift": 3.8356973144214845,
        "fitness": 0.0015632993530488068
    },
    {
        "parameters": {
            "Ppt_mm_Tot": {
                "lower_bound": 0.0,
                "upper_bound": 1.2330055701529212
            },
            "Relative_Humidity_Max": {
                "lower_bound": 62.75680274362891,
                "upper_bound": 64.13814857803537
            }
        },
        "support": 0.006222547584187409,
        "confidence": 0.4722222222222222,
        "lift": 1.9970760233918128,
        "fitness": 0.00015465396042571044
    },
    {
        "parameters": {
            "Ppt_mm_Tot": {
                "lower_bound": 0.0,
                "upper_bound": 1.2353541840212297
            }
        },
        "support": 0.229502196193265,
        "confidence": 0.29673450070989116,
        "lift": 1.2549205200300662,
        "fitness": 0.1321964851043915
    },
    {
        "parameters": {
            "Ppt_mm_Tot": {
                "lower_bound": 0.0,
                "upper_bound": 1.266162107682795
            }
        },
        "support": 0.229502196193265,
        "confidence": 0.29673450070989116,
        "lift": 1.2549205200300662,
        "fitness": 0.1321964851043915
    },
    {
        "parameters": {
            "Ppt_mm_Tot": {
                "lower_bound": 0.0,
                "upper_bound": 1.2606328488062293
            }
        },
        "support": 0.229502196193265,
        "confidence": 0.29673450070989116,
        "lift": 1.2549205200300662,
        "fitness": 0.1321964851043915
    },
    {
        "parameters": {
            "Ppt_mm_Tot": {
                "lower_bound": 0.0,
                "upper_bound": 1.2353541840212297
            }
        },
        "support": 0.229502196193265,
        "confidence": 0.29673450070989116,
        "lift": 1.2549205200300662,
        "fitness": 0.1321964851043915
    },
    {
        "parameters": {
            "Ppt_mm_Tot": {
                "lower_bound": 0.0,
                "upper_bound": 1.2708427959783684
            }
        },
        "support": 0.229502196193265,
        "confidence": 0.29673450070989116,
        "lift": 1.2549205200300662,
        "fitness": 0.1321964851043915
    },
    {
        "parameters": {
            "Ppt_mm_Tot": {
                "lower_bound": 0.0,
                "upper_bound": 1.2606328488062293
            }
        },
        "support": 0.229502196193265,
        "confidence": 0.29673450070989116,
        "lift": 1.2549205200300662,
        "fitness": 0.1321964851043915
    },
    {
        "parameters": {
            "Ppt_mm_Tot": {
                "lower_bound": 0.0,
                "upper_bound": 1.2606328488062293
            }
        },
        "support": 0.229502196193265,
        "confidence": 0.29673450070989116,
        "lift": 1.2549205200300662,
        "fitness": 0.1321964851043915
    },
    {
        "parameters": {
            "Ppt_mm_Tot": {
                "lower_bound": 0.0,
                "upper_bound": 1.2101865142129238
            }
        },
        "support": 0.229502196193265,
        "confidence": 0.29673450070989116,
        "lift": 1.2549205200300662,
        "fitness": 0.1321964851043915
    },
    {
        "parameters": {
            "Ppt_mm_Tot": {
                "lower_bound": 0.0,
                "upper_bound": 1.2101865142129238
            }
        },
        "support": 0.229502196193265,
        "confidence": 0.29673450070989116,
        "lift": 1.2549205200300662,
        "fitness": 0.1321964851043915
    },
    {
        "parameters": {
            "Ppt_mm_Tot": {
                "lower_bound": 0.0,
                "upper_bound": 1.0512800881935995
            }
        },
        "support": 0.2287701317715959,
        "confidence": 0.2976190476190476,
        "lift": 1.2586613592805544,
        "fitness": 0.13174603084664552
    },
    {
        "parameters": {
            "Ppt_mm_Tot": {
                "lower_bound": 0.21097853424992974,
                "upper_bound": 1.2868642099053065
            }
        },
        "support": 0.0036603221083455345,
        "confidence": 0.1282051282051282,
        "lift": 0.5421925855362387,
        "fitness": 1.452854690936546e-05
    },
    {
        "parameters": {
            "Ppt_mm_Tot": {
                "lower_bound": 0.0,
                "upper_bound": 1.2708427959783684
            }
        },
        "support": 0.229502196193265,
        "confidence": 0.29673450070989116,
        "lift": 1.2549205200300662,
        "fitness": 0.1321964851043915
    },
    {
        "parameters": {
            "Ppt_mm_Tot": {
                "lower_bound": 0.0,
                "upper_bound": 1.2198757314238067
            },
            "Air_TempC_Min": {
                "lower_bound": 14.399397496414396,
                "upper_bound": 15.039679809140354
            }
        },
        "support": 0.0,
        "confidence": 0.0,
        "lift": 0.0,
        "fitness": 0.0
    },
    {
        "parameters": {
            "Ppt_mm_Tot": {
                "lower_bound": 0.0,
                "upper_bound": 1.2907263409235639
            }
        },
        "support": 0.229502196193265,
        "confidence": 0.29673450070989116,
        "lift": 1.2549205200300662,
        "fitness": 0.1321964851043915
    },
    {
        "parameters": {
            "Ppt_mm_Tot": {
                "lower_bound": 0.0,
                "upper_bound": 1.2568997681525282
            }
        },
        "support": 0.229502196193265,
        "confidence": 0.29673450070989116,
        "lift": 1.2549205200300662,
        "fitness": 0.1321964851043915
    },
    {
        "parameters": {
            "Ppt_mm_Tot": {
                "lower_bound": 0.0,
                "upper_bound": 1.2591384149762956
            }
        },
        "support": 0.229502196193265,
        "confidence": 0.29673450070989116,
        "lift": 1.2549205200300662,
        "fitness": 0.1321964851043915
    },
    {
        "parameters": {
            "Ppt_mm_Tot": {
                "lower_bound": 0.0,
                "upper_bound": 1.2330055701529212
            }
        },
        "support": 0.229502196193265,
        "confidence": 0.29673450070989116,
        "lift": 1.2549205200300662,
        "fitness": 0.1321964851043915
    },
    {
        "parameters": {
            "Ppt_mm_Tot": {
                "lower_bound": 0.0,
                "upper_bound": 1.2708427959783684
            }
        },
        "support": 0.229502196193265,
        "confidence": 0.29673450070989116,
        "lift": 1.2549205200300662,
        "fitness": 0.1321964851043915
    },
    {
        "parameters": {
            "Ppt_mm_Tot": {
                "lower_bound": 0.0,
                "upper_bound": 1.093074854381722
            }
        },
        "support": 0.2287701317715959,
        "confidence": 0.2976190476190476,
        "lift": 1.2586613592805544,
        "fitness": 0.13174603084664552
    },
    {
        "parameters": {
            "Ppt_mm_Tot": {
                "lower_bound": 0.0,
                "upper_bound": 1.2708427959783684
            }
        },
        "support": 0.229502196193265,
        "confidence": 0.29673450070989116,
        "lift": 1.2549205200300662,
        "fitness": 0.1321964851043915
    },
    {
        "parameters": {
            "Ppt_mm_Tot": {
                "lower_bound": 0.0,
                "upper_bound": 1.2536011216338179
            }
        },
        "support": 0.229502196193265,
        "confidence": 0.29673450070989116,
        "lift": 1.2549205200300662,
        "fitness": 0.1321964851043915
    },
    {
        "parameters": {
            "Ppt_mm_Tot": {
                "lower_bound": 0.0,
                "upper_bound": 1.2907263409235639
            }
        },
        "support": 0.229502196193265,
        "confidence": 0.29673450070989116,
        "lift": 1.2549205200300662,
        "fitness": 0.1321964851043915
    },
    {
        "parameters": {
            "Ppt_mm_Tot": {
                "lower_bound": 0.0,
                "upper_bound": 1.2708427959783684
            }
        },
        "support": 0.229502196193265,
        "confidence": 0.29673450070989116,
        "lift": 1.2549205200300662,
        "fitness": 0.1321964851043915
    },
    {
        "parameters": {
            "Ppt_mm_Tot": {
                "lower_bound": 0.0,
                "upper_bound": 1.2868642099053065
            }
        },
        "support": 0.229502196193265,
        "confidence": 0.29673450070989116,
        "lift": 1.2549205200300662,
        "fitness": 0.1321964851043915
    },
    {
        "parameters": {
            "Ppt_mm_Tot": {
                "lower_bound": 0.0,
                "upper_bound": 1.2101865142129238
            }
        },
        "support": 0.229502196193265,
        "confidence": 0.29673450070989116,
        "lift": 1.2549205200300662,
        "fitness": 0.1321964851043915
    },
    {
        "parameters": {
            "Ppt_mm_Tot": {
                "lower_bound": 0.0,
                "upper_bound": 1.2101865142129238
            }
        },
        "support": 0.229502196193265,
        "confidence": 0.29673450070989116,
        "lift": 1.2549205200300662,
        "fitness": 0.1321964851043915
    },
    {
        "parameters": {
            "Ppt_mm_Tot": {
                "lower_bound": 0.0,
                "upper_bound": 1.266162107682795
            }
        },
        "support": 0.229502196193265,
        "confidence": 0.29673450070989116,
        "lift": 1.2549205200300662,
        "fitness": 0.1321964851043915
    },
    {
        "parameters": {
            "Ppt_mm_Tot": {
                "lower_bound": 0.0,
                "upper_bound": 0.9493845445764346
            }
        },
        "support": 0.22840409956076135,
        "confidence": 0.29770992366412213,
        "lift": 1.2590456833597239,
        "fitness": 0.13136487998749058
    },
    {
        "parameters": {
            "Ppt_mm_Tot": {
                "lower_bound": 0.0,
                "upper_bound": 1.2353541840212297
            }
        },
        "support": 0.229502196193265,
        "confidence": 0.29673450070989116,
        "lift": 1.2549205200300662,
        "fitness": 0.1321964851043915
    },
    {
        "parameters": {
            "Ppt_mm_Tot": {
                "lower_bound": 0.32593933286638194,
                "upper_bound": 1.2606328488062293
            }
        },
        "support": 0.003294289897510981,
        "confidence": 0.13636363636363635,
        "lift": 0.576695750070363,
        "fitness": 1.2517003550914226e-05
    },
    {
        "parameters": {
            "Ppt_mm_Tot": {
                "lower_bound": 0.0,
                "upper_bound": 1.2198757314238067
            }
        },
        "support": 0.229502196193265,
        "confidence": 0.29673450070989116,
        "lift": 1.2549205200300662,
        "fitness": 0.1321964851043915
    },
    {
        "parameters": {
            "Ppt_mm_Tot": {
                "lower_bound": 0.08976390982588547,
                "upper_bound": 1.2353541840212297
            }
        },
        "support": 0.011346998535871157,
        "confidence": 0.17032967032967034,
        "lift": 0.7203415779267173,
        "fitness": 0.0001854942604186742
    },
    {
        "parameters": {
            "Ppt_mm_Tot": {
                "lower_bound": 0.0,
                "upper_bound": 1.2868642099053065
            }
        },
        "support": 0.229502196193265,
        "confidence": 0.29673450070989116,
        "lift": 1.2549205200300662,
        "fitness": 0.1321964851043915
    }
]